{
  "wx.request": {
    "description": "网络请求"
  },
  "wx.uploadFile": {
    "description": "文件上传"
  },
  "wx.downloadFile": {
    "description": "文件下载"
  },
  "wx.connectSocket": {
    "description": "创建Socket连接"
  },
  "wx.onSocketOpen": {
    "description": "监听WebSocket连接打开事件"
  },
  "wx.onSocketError": {
    "description": "监听WebSocket错误"
  },
  "wx.sendSocketMessage": {
    "description":
      "通过 WebSocket 连接发送数据，需要先 wx.connectSocket，并在 wx.onSocketOpen 回调之后才能发送"
  },
  "wx.onSocketMessage": {
    "description": "监听WebSocket接受到服务器的消息事件"
  },
  "wx.closeSocket": {
    "description": "关闭 WebSocket 连接"
  },
  "wx.onSocketClose": {
    "description": "监听WebSocket关闭"
  },
  "wx.chooseImage": {
    "description": "从本地相册选择图片或使用相机拍照"
  },
  "wx.previewImage": {
    "description": "预览图片"
  },
  "wx.getImageInfo": {
    "description": "获取图片信息"
  },
  "wx.saveImageToPhotosAlbum": {
    "description": "保存图片到系统相册 需要用户授权 scope.writePhotosAlbum"
  },
  "wx.login": {
    "description": "调用接口wx.login() 获取临时登录凭证（code）"
  },
  "wx.checkSession": {
    "description": "校验用户当前session_key是否有效"
  },
  "wx.authorize": {
    "description":
      "提前向用户发起授权请求。调用后会立刻弹窗询问用户是否同意授权小程序使用某项功能或获取用户的某些数据，但不会实际调用对应接口。如果用户之前已经同意授权，则不会出现弹窗，直接返回成功。"
  },
  "wx.getUserInfo": {
    "description":
      "获取用户信息，withCredentials 为 true 时需要先调用 wx.login 接口。需要用户授权 scope.userInfo"
  },
  "wx.requestPayment": {
    "description": "发起微信支付"
  },
  "wx.onShareAppMessage": {
    "description": "在 Page 中定义 onShareAppMessage 函数，设置该页面的转发信息"
  },
  "wx.showShareMenu": {
    "description": "显示当前页面的转发按钮"
  },
  "wx.hideShareMenu": {
    "description": "隐藏当前页面的转发按钮"
  },
  "wx.updateShareMenu": {
    "description": "更新转发属性"
  },
  "wx.getShareInfo": {
    "description": "获取转发详细信息"
  },
  "wx.chooseAddress": {
    "description":
      "调起用户编辑收货地址原生界面，并在编辑完成后返回用户选择的地址 需要用户授权 scope.address"
  },
  "wx.addCard": {
    "description": "批量添加卡券"
  },
  "wx.openCard": {
    "description": "查看微信卡包中的卡券"
  },
  "wx.openSetting": {
    "description": "调起客户端小程序设置界面，返回用户设置的操作结果"
  },
  "wx.getSetting": {
    "description": "获取用户的当前设置"
  },
  "wx.getWeRunData": {
    "description":
      "获取用户过去三十天微信运动步数，需要先调用 wx.login 接口 需要用户授权 scope.werun"
  },
  "wx.navigateToMiniProgram": {
    "description":
      "打开同一公众号下关联的另一个小程序。（注：必须是同一公众号下，而非同个 open 账号下）"
  },
  "wx.navigateBackMiniProgram": {
    "description":
      "返回到上一个小程序，只有在当前小程序是被其他小程序打开时可以调用成功"
  },
  "wx.chooseInvoiceTitle": {
    "description": "选择用户的发票抬头 要用户授权 scope.invoiceTitle"
  },
  "wx.checkIsSupportSoterAuthentication": {
    "description": "获取本机支持的 SOTER 生物认证方式"
  },
  "wx.startSoterAuthentication": {
    "description": "开始 SOTER 生物认证"
  },
  "wx.checkIsSoterEnrolledInDevice": {
    "description": "获取设备内是否录入如指纹等生物信息的接口"
  },
  "wx.getExtConfig": {
    "description": "获取第三方平台自定义的数据字段。"
  },
  "wx.getExtConfigSync": {
    "description": "获取第三方平台自定义的数据字段的同步接口"
  },
  "wx.showToast": {
    "description": "显示消息提示框"
  },
  "wx.showLoading": {
    "description":
      "显示 loading 提示框, 需主动调用 wx.hideLoading 才能关闭提示框"
  },
  "wx.hideToast": {
    "description": "隐藏消息提示框"
  },
  "wx.hideLoading": {
    "description": "隐藏loading提示框"
  },
  "wx.showModal": {
    "description": "​显示模态弹窗"
  },
  "wx.showActionSheet": {
    "description": "​​显示操作菜单"
  },
  "wx.setNavigationBarTitle": {
    "description": "​​动态设置当前页面的标题"
  },
  "wx.showNavigationBarLoading": {
    "description": "在当前页面显示导航条加载动画"
  },
  "wx.hideNavigationBarLoading": {
    "description": "隐藏导航条加载动画"
  },
  "wx.setNavigationBarColor": {
    "description": "​​设置导航条颜色"
  },
  "wx.setTabBarBadge": {
    "description": "​​为 tabBar 某一项的右上角添加文本"
  },
  "wx.removeTabBarBadge": {
    "description": "​​移除 tabBar 某一项右上角的文本"
  },
  "wx.showTabBarRedDot": {
    "description": "​​显示 tabBar 某一项的右上角的红点"
  },
  "wx.hideTabBarRedDot": {
    "description": "​​隐藏 tabBar 某一项的右上角的红点"
  },
  "wx.setTabBarStyle": {
    "description": "​​动态设置 tabBar 的整体样式"
  },
  "wx.setTabBarItem": {
    "description": "​​动态设置 tabBar 某一项的内容"
  },
  "wx.showTabBar": {
    "description": "​​显示 tabBar"
  },
  "wx.hideTabBar": {
    "description": "​​隐藏 tabBar"
  },
  "wx.setTopBarText": {
    "description": "​​动态设置置顶栏文字内容，只有当前小程序被置顶时能生效"
  },
  "wx.navigateTo": {
    "description":
      "保留当前页面，跳转到应用内的某个页面，使用wx.navigateBack可以返回到原页面。"
  },
  "wx.redirectTo": {
    "description": "关闭当前页面，跳转到应用内的某个页面"
  },
  "wx.reLaunch": {
    "description": "关闭所有页面，打开到应用内的某个页面"
  },
  "wx.switchTab": {
    "description": "跳转到 tabBar 页面，并关闭其他所有非 tabBar 页面"
  },
  "wx.navigateBack": {
    "description":
      "关闭当前页面，返回上一页面或多级页面。可通过 getCurrentPages()) 获取当前的页面栈，决定需要返回几层"
  },
  "wx.createAnimation": {
    "description":
      "创建一个动画实例animation。调用实例的方法来描述动画。最后通过动画实例的export方法导出动画数据传递给组件的animation属性"
  },
  "wx.pageScrollTo": {
    "description": "将页面滚动到目标位置"
  },
  "wx.startPullDownRefresh": {
    "description":
      "开始下拉刷新，调用后触发下拉刷新动画，效果与用户手动下拉刷新一致"
  },
  "wx.stopPullDownRefresh": {
    "description": "停止下拉刷新"
  },
  "wx.makePhoneCall": {
    "description": "拨打电话"
  },
  "wx.getLocation": {
    "description":
      "获取当前的地理位置、速度。当用户离开小程序后，此接口无法调用；当用户点击“显示在聊天顶部”时，此接口可继续调用"
  },
  "wx.chooseLocation": {
    "description": "打开地图选择位置 需要用户授权 scope.userLocation"
  },
  "wx.openLocation": {
    "description": "使用微信内置地图查看位置 需要用户授权 scope.userLocation"
  },
  "wx.setStorage": {
    "description":
      "将数据存储在本地缓存中指定的 key 中，会覆盖掉原来该 key 对应的内容，这是一个异步接口"
  },
  "wx.setStorageSync": {
    "description":
      "将 data 存储在本地缓存中指定的 key 中，会覆盖掉原来该 key 对应的内容，这是一个同步接口"
  },
  "wx.getStorage": {
    "description": "从本地缓存中异步获取指定 key 对应的内容"
  },
  "wx.getStorageSync": {
    "description": "从本地缓存中同步获取指定 key 对应的内容"
  },
  "wx.getStorageInfo": {
    "description": "异步获取当前storage的相关信息"
  },
  "wx.getStorageInfoSync": {
    "description": "同步获取当前storage的相关信息"
  },
  "wx.removeStorage": {
    "description": "从本地缓存中异步移除指定 key"
  },
  "wx.removeStorageSync": {
    "description": "从本地缓存中同步移除指定 key"
  },
  "wx.clearStorage": {
    "description": "清理本地数据缓存"
  },
  "wx.clearStorageSync": {
    "description": "同步清理本地数据缓存"
  },
  "wx.saveFile": {
    "description":
      "保存文件到本地。注意：saveFile 会把临时文件移动，因此调用成功后传入的 tempFilePath 将不可用"
  },
  "wx.getFileInfo": {
    "description": "获取文件信息"
  },
  "wx.getSavedFileList": {
    "description": "获取本地已保存的文件列表"
  },
  "wx.getSavedFileInfo": {
    "description":
      "获取本地文件的文件信息。此接口只能用于获取已保存到本地的文件，若需要获取临时文件信息，请使用 wx.getFileInfo 接口"
  },
  "wx.removeSavedFile": {
    "description": "删除本地存储的文件"
  },
  "wx.openDocument": {
    "description":
      "新开页面打开文档，支持格式：doc, xls, ppt, pdf, docx, xlsx, pptx"
  },
  "wx.getSystemInfo": {
    "description": "获取系统信息"
  },
  "wx.getSystemInfoSync": {
    "description": "获取系统信息同步接口"
  },
  "wx.getNetworkType": {
    "description": "获取网络类型"
  },
  "wx.onNetworkStatusChange": {
    "description": "监听网络状态变化"
  },
  "wx.onAccelerometerChange": {
    "description":
      "监听加速度数据，频率：5次/秒，接口调用后会自动开始监听，可使用 wx.stopAccelerometer 停止监听"
  },
  "wx.startAccelerometer": {
    "description": "开始监听加速度数据"
  },
  "wx.stopAccelerometer": {
    "description": "停止监听加速度数据"
  },
  "wx.onCompassChange": {
    "description":
      "监听罗盘数据，频率：5次/秒，接口调用后会自动开始监听，可使用wx.stopCompass停止监听"
  },
  "wx.startCompass": {
    "description": "开始监听罗盘数据"
  },
  "wx.stopCompass": {
    "description": "停止监听罗盘数据"
  },
  "wx.scanCode": {
    "description": "调起客户端扫码界面，扫码成功后返回对应的结果"
  },
  "wx.setClipboardData": {
    "description": "设置系统剪贴板的内容"
  },
  "wx.getClipboardData": {
    "description": "获取系统剪贴板内容"
  },
  "wx.openBluetoothAdapter": {
    "description":
      "初始化小程序蓝牙模块，生效周期为调用wx.openBluetoothAdapter至调用wx.closeBluetoothAdapter或小程序被销毁为止"
  },
  "wx.closeBluetoothAdapter": {
    "description":
      "关闭蓝牙模块，使其进入未初始化状态。调用该方法将断开所有已建立的链接并释放系统资源"
  },
  "wx.getBluetoothAdapterState": {
    "description": "获取本机蓝牙适配器状态"
  },
  "wx.onBluetoothAdapterStateChange": {
    "description": "监听蓝牙适配器状态变化事件"
  },
  "wx.startBluetoothDevicesDiscovery": {
    "description":
      "开始搜寻附近的蓝牙外围设备。注意，该操作比较耗费系统资源，请在搜索并连接到设备后调用 stop 方法停止搜索"
  },
  "wx.stopBluetoothDevicesDiscovery": {
    "description":
      "停止搜寻附近的蓝牙外围设备。若已经找到需要的蓝牙设备并不需要继续搜索时，建议调用该接口停止蓝牙搜索"
  },
  "wx.getBluetoothDevices": {
    "description":
      "获取在小程序蓝牙模块生效期间所有已发现的蓝牙设备，包括已经和本机处于连接状态的设备"
  },
  "wx.onBluetoothDeviceFound": {
    "description": "监听寻找到新设备的事件"
  },
  "wx.getConnectedBluetoothDevices": {
    "description": "根据 uuid 获取处于已连接状态的设备"
  },
  "wx.createBLEConnection": {
    "description": "连接低功耗蓝牙设备"
  },
  "wx.closeBLEConnection": {
    "description": "断开与低功耗蓝牙设备的连接"
  },
  "wx.onBLEConnectionStateChange": {
    "description":
      "监听低功耗蓝牙连接状态的改变事件，包括开发者主动连接或断开连接，设备丢失，连接异常断开等等"
  },
  "wx.getBLEDeviceServices": {
    "description": "获取蓝牙设备所有 service（服务）"
  },
  "wx.getBLEDeviceCharacteristics": {
    "description": "获取蓝牙设备某个服务中的所有 characteristic（特征值）"
  },
  "wx.readBLECharacteristicValue": {
    "description":
      "读取低功耗蓝牙设备的特征值的二进制数据值。注意：必须设备的特征值支持read才可以成功调用，具体参照 characteristic 的 properties 属性"
  },
  "wx.writeBLECharacteristicValue": {
    "description":
      "读取低功耗蓝牙设备的特征值的二进制数据值。注意：必须设备的特征值支持read才可以成功调用，具体参照 characteristic 的 properties 属性"
  },
  "wx.notifyBLECharacteristicValueChange": {
    "description": "启用低功耗蓝牙设备特征值变化时的 notify 功能，订阅特征值"
  },
  "wx.onBLECharacteristicValueChange": {
    "description":
      "监听低功耗蓝牙设备的特征值变化。必须先启用notify接口才能接收到设备推送的notification"
  },
  "wx.startBeaconDiscovery": {
    "description": "开始搜索附近的iBeacon设备"
  },
  "wx.stopBeaconDiscovery": {
    "description": "停止搜索附近的iBeacon设备"
  },
  "wx.getBeacons": {
    "description": "获取所有已搜索到的iBeacon设备"
  },
  "wx.onBeaconUpdate": {
    "description": "监听 iBeacon 设备的更新事件"
  },
  "wx.onBeaconServiceChange": {
    "description": "监听 iBeacon 服务的状态变化"
  },
  "wx.setScreenBrightness": {
    "description": "设置屏幕亮度"
  },
  "wx.getScreenBrightness": {
    "description": "获取屏幕亮度"
  },
  "wx.setKeepScreenOn": {
    "description":
      "设置是否保持常亮状态。仅在当前小程序生效，离开小程序后设置失效"
  },
  "wx.onUserCaptureScreen": {
    "description": "监听用户主动截屏事件，用户使用系统截屏按键截屏时触发此事件"
  },
  "wx.vibrateLong": {
    "description": "使手机发生较长时间的振动（400ms）"
  },
  "wx.vibrateShort": {
    "description": "使手机发生较短时间的振动（15ms）"
  },
  "wx.getHCEState": {
    "description": "判断当前设备是否支持 HCE 能力"
  },
  "wx.startHCE": {
    "description": "初始化 NFC 模块"
  },
  "wx.stopHCE": {
    "description": "关闭 NFC 模块 仅在安卓系统下有效"
  },
  "wx.onHCEMessage": {
    "description": "监听 NFC 设备的消息回调，并在回调中处理"
  },
  "wx.sendHCEMessage": {
    "description": "发送 NFC 消息。仅在安卓系统下有效"
  },
  "wx.startWifi": {
    "description": "初始化 Wi-Fi 模块"
  },
  "wx.stopWifi": {
    "description": "关闭 Wi-Fi 模块"
  },
  "wx.connectWifi": {
    "description":
      "连接 Wi-Fi。若已知 Wi-Fi 信息，可以直接利用该接口连接。仅 Android 与 iOS 11 以上版本支持"
  },
  "wx.getWifiList": {
    "description": "请求获取 Wi-Fi 列表"
  },
  "wx.getConnectedWifi": {
    "description": "获取已连接中的 Wi-Fi 信息"
  },
  "wx.onGetWifiList": {
    "description":
      "监听在获取到 Wi-Fi 列表数据时的事件，在回调中将返回 wifiList"
  },
  "wx.onWifiConnected": {
    "description": "监听连接上 Wi-Fi 的事件"
  },
  "wx.setWifiList": {
    "description":
      "iOS特有接口 在 onGetWifiList 回调后，利用接口设置 wifiList 中 AP 的相关信息"
  }
}
